blase/__init__.py
blase/bag_index.npy
blase/bins.txt
blase/blase.py
blase/estimator.py
blase/models.pth
blase/parser.py
blase/scaling.npz
blase-0.3.1.dist-info/LICENSE.txt
blase-0.3.1.dist-info/METADATA
blase-0.3.1.dist-info/WHEEL
blase-0.3.1.dist-info/entry_points.txt
blase-0.3.1.dist-info/top_level.txt
blase-0.3.1.dist-info/RECORD
