Metadata-Version: 2.1
Name: blase
Version: 0.3.1
Summary: Synchtrotron peak estimator for blazars
Home-page: https://github.com/tkerscher/blase
Author: Tobias Kerscher
Author-email: 88444139+tkerscher@users.noreply.github.com
License: MIT
Keywords: blazar synchrotron
Platform: UNKNOWN
Classifier: Development Status :: 4 - Beta
Classifier: Environment :: Console
Classifier: Intended Audience :: Science/Research
Classifier: License :: OSI Approved :: MIT License
Classifier: Topic :: Scientific/Engineering :: Astronomy
License-File: LICENSE.txt
Requires-Dist: numpy
Requires-Dist: scipy
Requires-Dist: torch
Requires-Dist: tqdm
